PyShapeArea1/__init__.py
PyShapeArea1/core.py
PyShapeArea1/tests.py
pyshapearea-0.0.1.dist-info/METADATA
pyshapearea-0.0.1.dist-info/WHEEL
pyshapearea-0.0.1.dist-info/top_level.txt
pyshapearea-0.0.1.dist-info/RECORD
