Metadata-Version: 2.1
Name: pyshapearea
Version: 0.0.1
Summary: Module for calculating the area of shapes
Home-page: https://github.com/V1sl3t/PyShapeArea
Author: V1sl3t
Author-email: suppes214@gmail.com
Project-URL: GitHub, https://github.com/V1sl3t
Classifier: Programming Language :: Python :: 3.11
Requires-Python: >=3.6
